examples/__init__.py
examples/bad_declaration.py
examples/findlineset.py
examples/findliterals.py
examples/formatvrml.py
examples/jsonwcomments.py
examples/lisp.py
examples/prebuilt_call.py
examples/printable-unicode.py
examples/py_ebnf.py
examples/simpleexample.py
examples/simpleexample2_1.py
examples/simpleexample2_2.py
examples/simpleexample2_3.py
examples/transformation.py
examples/vrml.py
examples/vrml_erronfail.py
simpleparse/__init__.py
simpleparse/baseparser.py
simpleparse/dispatchprocessor.py
simpleparse/error.py
simpleparse/generator.py
simpleparse/objectgenerator.py
simpleparse/parser.py
simpleparse/printers.py
simpleparse/processor.py
simpleparse/simpleparsegrammar.py
simpleparse/common/__init__.py
simpleparse/common/calendar_names.py
simpleparse/common/chartypes.py
simpleparse/common/comments.py
simpleparse/common/iso_date.py
simpleparse/common/iso_date_loose.py
simpleparse/common/numbers.py
simpleparse/common/phonetics.py
simpleparse/common/strings.py
simpleparse/common/timezone_names.py
simpleparse/stt/COPYRIGHT
simpleparse/stt/LICENSE
simpleparse/stt/__init__.py
simpleparse/stt/mxLicense.html
simpleparse/stt/Doc/eGenix-mx-Extensions.html
simpleparse/stt/Doc/mxLicense.html
simpleparse/stt/Doc/mxTextTools.html
simpleparse/stt/TextTools/COPYRIGHT
simpleparse/stt/TextTools/LICENSE
simpleparse/stt/TextTools/TextTools.py
simpleparse/stt/TextTools/__init__.py
simpleparse/stt/TextTools/Constants/Sets.py
simpleparse/stt/TextTools/Constants/TagTables.py
simpleparse/stt/TextTools/Constants/__init__.py
simpleparse/stt/TextTools/mxTextTools/__init__.py
simpleparse/stt/TextTools/mxTextTools/highcommands.h
simpleparse/stt/TextTools/mxTextTools/lowlevelcommands.h
simpleparse/stt/TextTools/mxTextTools/mx.h
simpleparse/stt/TextTools/mxTextTools/mxTextTools.c
simpleparse/stt/TextTools/mxTextTools/mxTextTools.cp39-win_amd64.pyd
simpleparse/stt/TextTools/mxTextTools/mxTextTools.h
simpleparse/stt/TextTools/mxTextTools/mxbmse.c
SimpleParse-2.2.4.dist-info/METADATA
SimpleParse-2.2.4.dist-info/WHEEL
SimpleParse-2.2.4.dist-info/license.txt
SimpleParse-2.2.4.dist-info/top_level.txt
SimpleParse-2.2.4.dist-info/RECORD
